kn10/__init__.py
kn10-1.0.1.dist-info/licenses/LICENSE
kn10-1.0.1.dist-info/METADATA
kn10-1.0.1.dist-info/WHEEL
kn10-1.0.1.dist-info/top_level.txt
kn10-1.0.1.dist-info/RECORD
