Metadata-Version: 2.4
Name: kn10
Version: 1.0.1
Summary: 10KN: A compact, fixed-width numeric encoding system using digits and Hangul.
Author-email: blueradiance <your@email.com>
License: Other/Proprietary License (CUSTOM LICENSE FOR 10KN)
Keywords: numeric,encoding,korean,hangul,compression,10KN
Classifier: Programming Language :: Python :: 3
Classifier: License :: Other/Proprietary License
Classifier: Operating System :: OS Independent
Requires-Python: >=3.7
License-File: LICENSE
Dynamic: license-file
